{"cameraMode":{"drawMode":0,"name":"Shaded","section":"Shading Mode"},"sceneLighting":true,"audioPlay":false,"sceneViewState":{"m_AlwaysRefresh":false,"showFog":true,"showSkybox":true,"showFlares":true,"showImageEffects":true,"showParticleSystems":true,"showVisualEffectGraphs":true,"m_FxEnabled":true},"in2DMode":false,"pivot":{"x":14.548583984375,"y":10.766047477722168,"z":16.58622932434082},"rotation":{"x":-0.07179874926805496,"y":0.920904278755188,"z":-0.20381495356559754,"w":-0.3244105577468872},"size":9.550000190734864,"orthographic":false}